vk_types/__init__.py
vk_types/application.py
vk_types/appwidget.py
vk_types/base.py
vk_types/chat.py
vk_types/community.py
vk_types/conversation.py
vk_types/message.py
vk_types/user.py
vk_types/wall_comment.py
vk_types/wall_post.py
vk_types/additional/__init__.py
vk_types/additional/active_offer.py
vk_types/additional/admin_level.py
vk_types/additional/audio_genres.py
vk_types/additional/bdate.py
vk_types/additional/block_reason.py
vk_types/additional/city.py
vk_types/additional/country.py
vk_types/additional/donut.py
vk_types/additional/email.py
vk_types/additional/join_type.py
vk_types/additional/metro_station.py
vk_types/additional/name_request.py
vk_types/additional/photo_sizes.py
vk_types/additional/place.py
vk_types/additional/post_source.py
vk_types/additional/sex.py
vk_types/attachments/__init__.py
vk_types/attachments/album.py
vk_types/attachments/app.py
vk_types/attachments/attachments.py
vk_types/attachments/audio.py
vk_types/attachments/audio_msg.py
vk_types/attachments/document.py
vk_types/attachments/event.py
vk_types/attachments/geo.py
vk_types/attachments/gift.py
vk_types/attachments/graffiti.py
vk_types/attachments/like.py
vk_types/attachments/link.py
vk_types/attachments/market.py
vk_types/attachments/market_album.py
vk_types/attachments/note.py
vk_types/attachments/page.py
vk_types/attachments/photo.py
vk_types/attachments/poll.py
vk_types/attachments/pretty_cards.py
vk_types/attachments/repost.py
vk_types/attachments/sticker.py
vk_types/attachments/topic.py
vk_types/attachments/video.py
vk_types/events/__init__.py
vk_types/events/community/__init__.py
vk_types/events/community/event.py
vk_types/events/community/events_list.py
vk_types/events/community/events_objects.py
vk_types/responses/__init__.py
vk_types/responses/account.py
vk_types/responses/apps.py
vk_types/responses/appwidgets.py
vk_types/responses/auth.py
vk_types/responses/board.py
vk_types/responses/database.py
vk_types/responses/docs.py
vk_types/responses/fave.py
vk_types-0.2.5.1.dist-info/LICENSE
vk_types-0.2.5.1.dist-info/METADATA
vk_types-0.2.5.1.dist-info/WHEEL
vk_types-0.2.5.1.dist-info/top_level.txt
vk_types-0.2.5.1.dist-info/RECORD
