Metadata-Version: 2.1
Name: vk_types
Version: 0.2.5.1
Summary: vk_types for vk json answers
Home-page: https://github.com/kz159/vk_types
Author: kz159
Classifier: Programming Language :: Python :: 3
Classifier: Programming Language :: Python :: 3.8
Classifier: Programming Language :: Python :: 3.9
Classifier: License :: OSI Approved :: MIT License
Classifier: Operating System :: OS Independent
License-File: LICENSE
